[{
    "message": "&nbsp;&nbsp;&nbsp;&nbsp;&nbsp;&nbsp;&nbsp;&nbsp;&nbsp;&nbsp;&nbsp;&nbsp;&nbsp;&nbsp;&nbsp;&nbsp;&nbsp;&nbsp;&nbsp;&nbsp;",
        "number": 999,
        "section": "NULL",
        "target": "NULL"
}, {
    "message": "Raise your hand toward the ceiling.",
        "number": 1,
        "section": "A",
        "target": "environment"
}, {
    "message": "Lower your hand toward the floor.",
        "number": 2,
        "section": "A",
        "target": "environment"
}, {
    "message": "Draw a large plus sign in the air in front of you.",
        "number": 3,
        "section": "A",
        "target": "environment"
}, {
    "message": "Draw a large “X” in the air in front of you.",
        "number": 4,
        "section": "A",
        "target": "environment"
}, {
    "message": "Point straight in front of you and draw a spiral that slowly gets wider and wider, until you are drawing a large circle.",
        "number": 5,
        "section": "A",
        "target": "environment"
}, {
    "message": "Touch your opposite shoulder.",
        "number": 6,
        "section": "A",
        "target": "body"
}, {
    "message": "Touch your belly.",
        "number": 7,
        "section": "A",
        "target": "body"
}, {
    "message": "Pick up the cup in front of you and slowly take a sip of water. Once you are done set the cup down </br><b>(1 of 3)</b>",
        "number": 1,
        "section": "B",
        "target": "cup"
}, {
    "message": "Pick up the cup in front of you and slowly take a sip of water. Once you are done set the cup down </br><b>(2 of 3)</b>",
        "number": 2,
        "section": "B",
        "target": "cup"
}, {
    "message": "Pick up the cup in front of you and slowly take a sip of water. Once you are done set the cup down </br><b>(3 of 3)</b>",
        "number": 3,
        "section": "B",
        "target": "cup"
}, {
    "message": "Eat one of the items of food in front of you </br><b>(1 of 3)</b>",
        "number": 4,
        "section": "B",
        "target": "food"
}, {
    "message": "Eat one of the items of food in front of you </br><b>(2 of 3)</b>",
        "number": 5,
        "section": "B",
        "target": "food"
}, {
    "message": "Eat one of the items of food in front of you </br><b>(3 of 3)</b>",
        "number": 6,
        "section": "B",
        "target": "food"
}, {
    "message": "Pretend to bite your nails for a few seconds </br><b>(1 of 3)</b>",
        "number": 7,
        "section": "B",
        "target": "nails"
}, {
    "message": "Pretend to bite your nails for a few seconds </br><b>(2 of 3)</b>",
        "number": 8,
        "section": "B",
        "target": "nails"
}, {
    "message": "Pretend to bite your nails for a few seconds </br><b>(3 of 3)</b>",
        "number": 9,
        "section": "B",
        "target": "nails"
}, {
    "message": "Pretend to smoke a cigarette for a few seconds </br><b>(1 of 3)</b>",
        "number": 10,
        "section": "B",
        "target": "smoke"
}, {
    "message": "Pretend to smoke a cigarette for a few seconds </br><b>(2 of 3)</b>",
        "number": 11,
        "section": "B",
        "target": "smoke"
}, {
    "message": "Pretend to smoke a cigarette for a few seconds </br><b>(3 of 3)</b>",
        "number": 12,
        "section": "B",
        "target": "smoke"
}, {
    "message": "Pretend to pluck hair from your eyebrow for a few seconds </br><b>(1 of 3)</b>",
        "number": 13,
        "section": "B",
        "target": "eyebrow"
}, {
    "message": "Pretend to pluck hair from your eyebrow for a few seconds </br><b>(2 of 3)</b>",
        "number": 14,
        "section": "B",
        "target": "eyebrow"
}, {
    "message": "Pretend to pluck hair from your eyebrow for a few seconds </br><b>(3 of 3)</b>",
        "number": 15,
        "section": "B",
        "target": "eyebrow"
}, {
    "message": "Pretend to pick your nose by rubbing your nostril for a few seconds </br><b>(1 of 3)</b>",
        "number": 16,
        "section": "B",
        "target": "nose"
}, {
    "message": "Pretend to pick your nose by rubbing your nostril for a few seconds </br><b>(2 of 3)</b>",
        "number": 17,
        "section": "B",
        "target": "nose"
}, {
    "message": "Pretend to pick your nose by rubbing your nostril for a few seconds </br><b>(3 of 3)</b>",
        "number": 18,
        "section": "B",
        "target": "nose"
}, {
    "message": "Pretend to pluck your hair or scratch your scalp ABOVE your ear for a few second </br><b>(1 of 3)</b>",
        "number": 19,
        "section": "B",
        "target": "above-ear"
}, {
    "message": "Pretend to pluck your hair or scratch your scalp ABOVE your ear for a few second </br><b>(2 of 3)</b>",
        "number": 20,
        "section": "B",
        "target": "above-ear"
}, {
    "message": "Pretend to pluck your hair or scratch your scalp ABOVE your ear for a few second </br><b>(3 of 3)</b>",
        "number": 21,
        "section": "B",
        "target": "above-ear"
}, {
    "message": "Pretend to pluck your hair or scratch your scalp BEHIND your ear for a few seconds </br><b>(1 of 3)</b>",
        "number": 22,
        "section": "B",
        "target": "behind-ear"
}, {
    "message": "Pretend to pluck your hair or scratch your scalp BEHIND your ear for a few seconds </br><b>(2 of 3)</b>",
        "number": 23,
        "section": "B",
        "target": "behind-ear"
}, {
    "message": "Pretend to pluck your hair or scratch your scalp BEHIND your ear for a few seconds </br><b>(3 of 3)</b>",
        "number": 24,
        "section": "B",
        "target": "behind-ear"
}, {
    "message": "Pretend to pick your skin on your OPPOSITE cheek for a few seconds </br><b>(1 of 3)</b>",
        "number": 25,
        "section": "B",
        "target": "opposite-cheek"
}, {
    "message": "Pretend to pick your skin on your OPPOSITE cheek for a few seconds </br><b>(2 of 3)</b>",
        "number": 26,
        "section": "B",
        "target": "opposite-cheek"
}, {
    "message": "Pretend to pick your skin on your OPPOSITE cheek for a few seconds </br><b>(3 of 3)</b>",
        "number": 27,
        "section": "B",
        "target": "opposite-cheek"
}, {
    "message": "Touch your chin, and while touching your chin, draw a circle with your same elbow.  Keep rotating for 30 seconds.",
        "number": 1,
        "section": "C",
        "target": "chin"
}, {
    "message": "Touch the outside of your nostril and draw a circle with your elbow for 30 seconds.",
        "number": 2,
        "section": "C",
        "target": "nose"
}, {
    "message": "Touch the outside of your cheek and draw a circle with your elbow for 30 seconds.",
        "number": 3,
        "section": "C",
        "target": "cheek"
}, {
    "message": "Touch your eyebrow and draw a circle with your elbow for 30 seconds.",
        "number": 4,
        "section": "C",
        "target": "eyebrow"
}, {
    "message": "Touch ABOVE your ear and draw a circle with your elbow for 30 seconds.",
        "number": 5,
        "section": "C",
        "target": "above-ear"
}, {
    "message": "Touch BEHIND your ear and draw a circle with your elbow for 30 seconds.",
        "number": 6,
        "section": "C",
        "target": "behind-ear"
}, {
    "message": "Touch the top of your forehead at your hairline and draw a circle with your elbow for 30 seconds",
        "number": 7,
        "section": "C",
        "target": "forehead"
}, {
    "message": "Touch the top of your head and draw a circle with your elbow for 30 seconds.",
        "number": 8,
        "section": "C",
        "target": "top-head"
}, {
    "message": "Touch the back of your head and draw a circle with your elbow for 30 seconds.",
        "number": 9,
        "section": "C",
        "target": "back-head"
}, {
    "message": "Run your hand up and down the OPPOSITE side of your face for 30 seconds.",
        "number": 10,
        "section": "C",
        "target": "opposite-face"
}, {
    "message": "Paint three circles AROUND your mouth, without touching your mouth </br><b>(1 of 3)</b>",
        "number": 1,
        "section": "D",
        "target": "paint-mouth"
}, {
    "message": "Paint three circles AROUND your mouth, without touching your mouth </br><b>(2 of 3)</b>",
        "number": 2,
        "section": "D",
        "target": "paint-mouth"
}, {
    "message": "Paint three circles AROUND your mouth, without touching your mouth </br><b>(3 of 3)</b>",
        "number": 3,
        "section": "D",
        "target": "paint-mouth"
}, {
    "message": "Paint three circles AROUND your eyebrow, without touching your eyebrow </br><b>(1 of 3)</b>",
        "number": 4,
        "section": "D",
        "target": "paint-eyebrow"
}, {
    "message": "Paint three circles AROUND your eyebrow, without touching your eyebrow </br><b>(2 of 3)</b>",
        "number": 5,
        "section": "D",
        "target": "paint-eyebrow"
}, {
    "message": "Paint three circles AROUND your eyebrow, without touching your eyebrow </br><b>(3 of 3)</b>",
        "number": 6,
        "section": "D",
        "target": "paint-eyebrow"
}, {
    "message": "Paint three circles AROUND the area of scalp ABOVE your ear, without touching that area of the scalp </br><b>(1 of 3)</b>",
        "number": 7,
        "section": "D",
        "target": "paint-above-ear"
}, {
    "message": "Paint three circles AROUND the area of scalp ABOVE your ear, without touching that area of the scalp </br><b>(2 of 3)</b>",
        "number": 8,
        "section": "D",
        "target": "paint-above-ear"
}, {
    "message": "Paint three circles AROUND the area of scalp ABOVE your ear, without touching that area of the scalp </br><b>(3 of 3)</b>",
        "number": 9,
        "section": "D",
        "target": "paint-above-ear"
}, {
    "message": "Paint three circles AROUND the area of scalp BEHIND your ear, without touching that area of the scalp </br><b>(1 of 3)</b>",
        "number": 10,
        "section": "D",
        "target": "paint-behind-ear"
}, {
    "message": "Paint three circles AROUND the area of scalp BEHIND your ear, without touching that area of the scalp </br><b>(2 of 3)</b>",
        "number": 11,
        "section": "D",
        "target": "paint-behind-ear"
}, {
    "message": "Paint three circles AROUND the area of scalp BEHIND your ear, without touching that area of the scalp </br><b>(3 of 3)</b>",
        "number": 12,
        "section": "D",
        "target": "paint-behind-ear"
}, {
    "message": "Paint three circles AROUND your OPPOSITE cheek, without touching your cheek </br><b>(1 of 3)</b>",
        "number": 13,
        "section": "D"
}, {
    "message": "Paint three circles AROUND your OPPOSITE cheek, without touching your cheek </br><b>(2 of 3)</b>",
        "number": 14,
        "section": "D",
        "target": "paint-opposite-cheek"
}, {
    "message": "Paint three circles AROUND your OPPOSITE cheek, without touching your cheek </br><b>(3 of 3)</b>",
        "number": 15,
        "section": "D",
        "target": "paint-opposite-cheek"
}, {
    "message": "&nbsp;&nbsp;&nbsp;&nbsp;&nbsp;&nbsp;&nbsp;&nbsp;&nbsp;&nbsp;&nbsp;&nbsp;&nbsp;&nbsp;&nbsp;&nbsp;&nbsp;&nbsp;&nbsp;&nbsp;",
        "number": 999,
        "section": "NULL",
        "target": "NULL"
}]